[{"name":"Alive",
"image":"../../grunge-rock(2)/songs-images/a2s1.jpg",
"audio":"../../grunge-rock(2)/songs/A2S1.mp3"},
{"name":"Even Flow",
"image":"../../grunge-rock(2)/songs-images/a2s2.jpg",
"audio":"../../grunge-rock(2)/songs/A2S2.mp3"},
{"name":"Jeremy",
"image":"../../grunge-rock(2)/songs-images/a2s3.jpg",
"audio":"../../grunge-rock(2)/songs/A2S3.mp3"},
{"name":"Black",
"image":"../../grunge-rock(2)/songs-images/a2s4.jpg",
"audio":"../../grunge-rock(2)/songs/A2S4.mp3"},
{"name":"Ocean",
"image":"../../grunge-rock(2)/songs-images/a2s5.jpg",
"audio":"../../grunge-rock(2)/songs/A2S5.mp3"},
{"name":"Garden",
"image":"../../grunge-rock(2)/songs-images/a2s6.jpg",
"audio":"../../grunge-rock(2)/songs/A2S6.mp3"},
{"name":"Porch",
"image":"../../grunge-rock(2)/songs-images/a2s7.jpg",
"audio":"../../grunge-rock(2)/songs/A2S7.mp3"}
]